mtcnnruntime/__init__.py
mtcnnruntime/detector.py
mtcnnruntime/weights/onet.onnx
mtcnnruntime/weights/pnet.onnx
mtcnnruntime/weights/rnet.onnx
mtcnn_runtime-1.0.0.dist-info/METADATA
mtcnn_runtime-1.0.0.dist-info/WHEEL
mtcnn_runtime-1.0.0.dist-info/licenses/LICENSE
mtcnn_runtime-1.0.0.dist-info/RECORD
